ssmode/__init__.py
ssmode/bar_chart.py
ssmode/constants.py
ssmode/kpi.py
ssmode/line_chart.py
ssmode/quote_pruning.py
ssmode/tables.py
ssmode-0.1.6.dist-info/LICENSE
ssmode-0.1.6.dist-info/METADATA
ssmode-0.1.6.dist-info/WHEEL
ssmode-0.1.6.dist-info/top_level.txt
ssmode-0.1.6.dist-info/RECORD
