Metadata-Version: 2.1
Name: ssmode
Version: 0.1.6
Summary: Tools for use in Mode Analytics Jupyter Notebooks
Home-page: https://github.com/skyselect/ssmode
Author: SkySelect, Inc.
Author-email: oss@skyselect.com
License: UNKNOWN
Platform: UNKNOWN
Classifier: Programming Language :: Python :: 3
Classifier: License :: OSI Approved :: MIT License
Classifier: Operating System :: OS Independent
Requires-Python: >=3.6
